tailcalib.py
tailcalib-0.0.1.dist-info/LICENSE
tailcalib-0.0.1.dist-info/METADATA
tailcalib-0.0.1.dist-info/WHEEL
tailcalib-0.0.1.dist-info/top_level.txt
tailcalib-0.0.1.dist-info/RECORD
