Metadata-Version: 2.1
Name: tailcalib
Version: 0.0.1
Summary: tailcalib is a Python library for balancing a long-tailed / imbalanced dataset by generating synthetic datapoints which will inturn increase the class-wise and overall test accuracy on the original dataset.
Home-page: UNKNOWN
Author: Rahul Vigneswaran
License: UNKNOWN
Platform: UNKNOWN
Classifier: Programming Language :: Python :: 3
Classifier: License :: OSI Approved :: MIT License
Classifier: Operating System :: OS Independent
Requires-Python: >=3.6
License-File: LICENSE
Requires-Dist: numpy
Requires-Dist: scikit-learn
